<annotation>
	<folder>train</folder>
	<filename>3f0c935a-3b58-417a-9d2e-25f1ea7ba7bb.jpg</filename>
	<path>C:\tensorflow1\models\research\object_detection\images\train\3f0c935a-3b58-417a-9d2e-25f1ea7ba7bb.jpg</path>
	<source>
		<database>Unknown</database>
	</source>
	<size>
		<width>150</width>
		<height>200</height>
		<depth>3</depth>
	</size>
	<segmented>0</segmented>
	<object>
		<name>Centik Buskopan</name>
		<pose>Unspecified</pose>
		<truncated>0</truncated>
		<difficult>0</difficult>
		<bndbox>
			<xmin>55</xmin>
			<ymin>94</ymin>
			<xmax>69</xmax>
			<ymax>120</ymax>
		</bndbox>
	</object>
</annotation>
